dana/__init__.py
dana/api_client.py
dana/api_response.py
dana/exceptions.py
dana/rest.py
dana/base/__init__.py
dana/base/configuration.py
dana/base/model.py
dana/base/types.py
dana/ipg/__init__.py
dana/ipg/v1/__init__.py
dana/ipg/v1/enum.py
dana/ipg/v1/api/__init__.py
dana/ipg/v1/api/ipg_api.py
dana/ipg/v1/models/__init__.py
dana/ipg/v1/models/account_unbinding_request.py
dana/ipg/v1/models/account_unbinding_request_additional_info.py
dana/ipg/v1/models/account_unbinding_response.py
dana/ipg/v1/models/amount_detail.py
dana/ipg/v1/models/apply_ott_request.py
dana/ipg/v1/models/apply_ott_request_additional_info.py
dana/ipg/v1/models/apply_ott_response.py
dana/ipg/v1/models/apply_ott_response_user_resources_inner.py
dana/ipg/v1/models/apply_token_authorization_code_request.py
dana/ipg/v1/models/apply_token_refresh_token_request.py
dana/ipg/v1/models/apply_token_response.py
dana/ipg/v1/models/apply_token_response_additional_info.py
dana/ipg/v1/models/apply_token_response_additional_info_user_info.py
dana/ipg/v1/models/buyer.py
dana/ipg/v1/models/cancel_order_request.py
dana/ipg/v1/models/cancel_order_response.py
dana/ipg/v1/models/env_info.py
dana/ipg/v1/models/goods.py
dana/ipg/v1/models/international_order_info.py
dana/ipg/v1/models/international_order_info_exchange_rate.py
dana/ipg/v1/models/ipg_payment_request.py
dana/ipg/v1/models/ipg_payment_request_additional_info.py
dana/ipg/v1/models/ipg_payment_response.py
dana/ipg/v1/models/money.py
dana/ipg/v1/models/order.py
dana/ipg/v1/models/pay_option_detail.py
dana/ipg/v1/models/pay_option_detail_additional_info.py
dana/ipg/v1/models/pay_option_info.py
dana/ipg/v1/models/payment_promo_info.py
dana/ipg/v1/models/payment_view.py
dana/ipg/v1/models/query_payment_request.py
dana/ipg/v1/models/query_payment_response.py
dana/ipg/v1/models/query_payment_response_additional_info.py
dana/ipg/v1/models/refund_order_request.py
dana/ipg/v1/models/refund_order_request_additional_info.py
dana/ipg/v1/models/refund_order_response.py
dana_python_api_client-0.2.17.dist-info/licenses/LICENSE
dana_python_api_client-0.2.17.dist-info/METADATA
dana_python_api_client-0.2.17.dist-info/WHEEL
dana_python_api_client-0.2.17.dist-info/top_level.txt
dana_python_api_client-0.2.17.dist-info/RECORD
