Metadata-Version: 2.4
Name: dana-python-api-client
Version: 0.2.17
Summary: API Client (SDK) for DANA APIs based on https://dashboard.dana.id/api-docs
Author-email: DANA Automation Team <automation@dana.id>, Rangga Putra Pertama <rangga.putra@dana.id>
Maintainer-email: DANA Automation Team <automation@dana.id>, Rangga Putra Pertama <rangga.putra@dana.id>
License-Expression: Apache-2.0
Project-URL: homepage, https://dashboard.dana.id/api-docs
Project-URL: repository, https://github.com/dana-id/python_client
Keywords: DANA,DANA ID Docs,DANA SDK,DANA Python,DANA API Client,DANA Python API Client,DANA Python SDK
Requires-Python: >3.9.1
License-File: LICENSE
Requires-Dist: annotated-types==0.7.0
Requires-Dist: cffi==1.17.1
Requires-Dist: cryptography==44.0.2
Requires-Dist: pycparser==2.22
Requires-Dist: pydantic==2.10.6
Requires-Dist: pydantic-core==2.27.2
Requires-Dist: python-dateutil==2.9.0.post0
Requires-Dist: six==1.17.0
Requires-Dist: typing-extensions==4.12.2
Requires-Dist: urllib3==2.3.0
Dynamic: license-file
